{
  "ok": [
    {
      "id": 102,
      "secondaryColourHex": "",
      "name": "AFC Wimbledon",
      "friendlyName": "AFC Wimbledon",
      "thirdColourHex": "",
      "abbreviatedName": "WIM",
      "shirtType": {
        "Filled": null
      },
      "primaryColourHex": ""
    },
    {
      "id": 82,
      "secondaryColourHex": "",
      "name": "Accrington Stanley FC",
      "friendlyName": "Accrington Stanley",
      "thirdColourHex": "",
      "abbreviatedName": "ACC",
      "shirtType": {
        "Filled": null
      },
      "primaryColourHex": ""
    },
    {
      "id": 99,
      "secondaryColourHex": "",
      "name": "Barrow AFC",
      "friendlyName": "Barrow",
      "thirdColourHex": "",
      "abbreviatedName": "BAR",
      "shirtType": {
        "Filled": null
      },
      "primaryColourHex": ""
    },
    {
      "id": 97,
      "secondaryColourHex": "",
      "name": "Bradford City AFC",
      "friendlyName": "Bradford City",
      "thirdColourHex": "",
      "abbreviatedName": "BRA",
      "shirtType": {
        "Filled": null
      },
      "primaryColourHex": ""
    },
    {
      "id": 106,
      "secondaryColourHex": "",
      "name": "Cheltenham Town FC",
      "friendlyName": "Cheltenham",
      "thirdColourHex": "",
      "abbreviatedName": "CHT",
      "shirtType": {
        "Filled": null
      },
      "primaryColourHex": ""
    },
    {
      "id": 96,
      "secondaryColourHex": "",
      "name": "Chesterfield FC",
      "friendlyName": "Chesterfield",
      "thirdColourHex": "",
      "abbreviatedName": "CHF",
      "shirtType": {
        "Filled": null
      },
      "primaryColourHex": ""
    },
    {
      "id": 95,
      "secondaryColourHex": "",
      "name": "Crewe Alexandra FC",
      "friendlyName": "Crewe Alexandra",
      "thirdColourHex": "",
      "abbreviatedName": "CRE",
      "shirtType": {
        "Filled": null
      },
      "primaryColourHex": ""
    },
    {
      "id": 94,
      "secondaryColourHex": "",
      "name": "Doncaster Rovers FC",
      "friendlyName": "Doncaster",
      "thirdColourHex": "",
      "abbreviatedName": "DON",
      "shirtType": {
        "Filled": null
      },
      "primaryColourHex": ""
    },
    {
      "id": 105,
      "secondaryColourHex": "",
      "name": "Fleetwood Town FC",
      "friendlyName": "Fleetwood Town",
      "thirdColourHex": "",
      "abbreviatedName": "FLT",
      "shirtType": {
        "Filled": null
      },
      "primaryColourHex": ""
    },
    {
      "id": 101,
      "secondaryColourHex": "",
      "name": "Gillingham FC",
      "friendlyName": "Gillingham",
      "thirdColourHex": "",
      "abbreviatedName": "GIL",
      "shirtType": {
        "Filled": null
      },
      "primaryColourHex": ""
    },
    {
      "id": 100,
      "secondaryColourHex": "",
      "name": "Grimsby Town FC",
      "friendlyName": "Grimsby Town",
      "thirdColourHex": "",
      "abbreviatedName": "GRI",
      "shirtType": {
        "Filled": null
      },
      "primaryColourHex": ""
    },
    {
      "id": 98,
      "secondaryColourHex": "",
      "name": "Milton Keynes Dons FC",
      "friendlyName": "MK Dons",
      "thirdColourHex": "",
      "abbreviatedName": "MKD",
      "shirtType": {
        "Filled": null
      },
      "primaryColourHex": ""
    },
    {
      "id": 85,
      "secondaryColourHex": "",
      "name": "Morecambe FC",
      "friendlyName": "Morecambe",
      "thirdColourHex": "",
      "abbreviatedName": "MCM",
      "shirtType": {
        "Filled": null
      },
      "primaryColourHex": ""
    },
    {
      "id": 104,
      "secondaryColourHex": "",
      "name": "Newport County AFC",
      "friendlyName": "Newport County",
      "thirdColourHex": "",
      "abbreviatedName": "NEW",
      "shirtType": {
        "Filled": null
      },
      "primaryColourHex": ""
    },
    {
      "id": 93,
      "secondaryColourHex": "",
      "name": "Notts County FC",
      "friendlyName": "Notts County",
      "thirdColourHex": "",
      "abbreviatedName": "NCO",
      "shirtType": {
        "Filled": null
      },
      "primaryColourHex": ""
    },
    {
      "id": 91,
      "secondaryColourHex": "",
      "name": "Port Vale FC",
      "friendlyName": "Port Vale",
      "thirdColourHex": "",
      "abbreviatedName": "POV",
      "shirtType": {
        "Filled": null
      },
      "primaryColourHex": ""
    },
    {
      "id": 103,
      "secondaryColourHex": "",
      "name": "Salford City FC",
      "friendlyName": "Salford City",
      "thirdColourHex": "",
      "abbreviatedName": "SAL",
      "shirtType": {
        "Filled": null
      },
      "primaryColourHex": ""
    },
    {
      "id": 72,
      "secondaryColourHex": "",
      "name": "Swindon Town FC",
      "friendlyName": "Swindon Town",
      "thirdColourHex": "",
      "abbreviatedName": "SWI",
      "shirtType": {
        "Filled": null
      },
      "primaryColourHex": ""
    },
    {
      "id": 92,
      "secondaryColourHex": "",
      "name": "Walsall FC",
      "friendlyName": "Walsall",
      "thirdColourHex": "",
      "abbreviatedName": "WAL",
      "shirtType": {
        "Filled": null
      },
      "primaryColourHex": ""
    }
  ]
}